gamslib/__init__.py
gamslib/objectdir.py
gamslib/py.typed
gamslib/Xvalidate/xml/resources/schemas/xlink.xsd
gamslib/formatdetect/__init__.py
gamslib/formatdetect/formatdetector.py
gamslib/formatdetect/formatinfo.py
gamslib/formatdetect/jsontypes.py
gamslib/formatdetect/magikadetector.py
gamslib/formatdetect/minimaldetector.py
gamslib/formatdetect/siegfrieddetector.py
gamslib/formatdetect/xmltypes.py
gamslib/formatdetect/resources/json_subformats.csv
gamslib/formatdetect/resources/pronom_formats.csv
gamslib/formatdetect/resources/readme.txt
gamslib/formatdetect/resources/xml_subformats.csv
gamslib/objectcsv/__init__.py
gamslib/objectcsv/create_csv.py
gamslib/objectcsv/defaultvalues.py
gamslib/objectcsv/dsdata.py
gamslib/objectcsv/dublincore.py
gamslib/objectcsv/exceptions.py
gamslib/objectcsv/manage_csv.py
gamslib/objectcsv/objectcollection.py
gamslib/objectcsv/objectcsvmanager.py
gamslib/objectcsv/objectdata.py
gamslib/objectcsv/utils.py
gamslib/objectcsv/xlsx.py
gamslib/projectconfiguration/__init__.py
gamslib/projectconfiguration/configuration.py
gamslib/projectconfiguration/utils.py
gamslib/projectconfiguration/resources/gitignore
gamslib/projectconfiguration/resources/project.toml
gamslib/sip/__init__.py
gamslib/sip/utils.py
gamslib/sip/resources/sip-schema-d1.json
gamslib/sip/validation/__init__.py
gamslib/sip/validation/baginfo.py
gamslib/sip/validation/bagit.py
gamslib/sip/validation/manifests.py
gamslib/sip/validation/sip_json.py
gamslib-0.7.12.dist-info/METADATA
gamslib-0.7.12.dist-info/WHEEL
gamslib-0.7.12.dist-info/licenses/LICENSE
gamslib-0.7.12.dist-info/RECORD
