Metadata-Version: 2.4
Name: gamslib
Version: 0.7.12
Summary: Modules and subpackages used in various GAMS5 related projects
Project-URL: Homepage, https://github.com/DHGraz/gamslib
Project-URL: Repository, https://github.com/DHGraz/gamslib
Project-URL: Issues, https://github.com/DHGraz/gamslib/issues
Project-URL: Changelog, https://github.com/DHGraz/gamslib/blob/main/CHANGELOG.md
Author-email: Gunter Vasold <gunter.vasold@uni-graz.at>, Fabio Tosques <fabio.tosques@uni-graz.at>
License-File: LICENSE
Keywords: GAMS
Classifier: Development Status :: 4 - Beta
Classifier: Intended Audience :: Developers
Classifier: License :: OSI Approved :: MIT License
Classifier: Programming Language :: Python :: 3.11
Classifier: Programming Language :: Python :: 3.12
Classifier: Programming Language :: Python :: 3.13
Classifier: Topic :: Software Development :: Libraries
Requires-Python: >=3.11
Requires-Dist: jsonschema>=4.25.1
Requires-Dist: lxml>=6.0.2
Requires-Dist: magika>=1.0.1
Requires-Dist: pydantic>=2.12.2
Requires-Dist: pygfried>=0.12.0
Requires-Dist: pylightxl>=1.61
Requires-Dist: python-dotenv>=1.1.1
Requires-Dist: requests>=2.32.5
Requires-Dist: rnc2rng>=2.7.0
Requires-Dist: tomlkit>=0.13.3
Requires-Dist: uritools>=5.0.0
